
  [{"email":"estevamseila07@gmail.com","denuncia":"sadasdawd"},{"email":"dasdasdas","denuncia":"asdasdasd"},{"apelido":"sdd","denu":"sddzd"},{"email":"guto@gmail.com","denuncia":"sdfjsdfhgsdhfgsdhfhsdf"},{"email":"eu@gmail.com","denuncia":"sdfjsdfhgsdhfgsdhfhsdf"},{"email":"eu@gmail.com","denuncia":"sdfjsdfhgsdhfgsdhfhsdf"},{"email":"eu@gmail.com","denuncia":"sdfjsdfhgsdhfgsdhfhsdf"},{"email":"eu@gmail.com","denuncia":"sdfjsdfhgsdhfgsdhfhsdf"},{"email":"eu@gmail.com","denuncia":"sdfjsdfhgsdhfgsdhfhsdf"},{"email":"eu@gmail.com","denuncia":"sdfjsdfhgsdhfgsdhfhsdf"},{"email":"eu@gmail.com","denuncia":"sdfjsdfhgsdhfgsdhfhsdf"},{"email":"eu@gmail.com","denuncia":"sdfjsdfhgsdhfgsdhfhsdf"},{"email":"dsfdsfdsf","denuncia":"sdfdsfdsfds"},{"email":"sdfdsfsdf","denuncia":"sdfsdfsdfsd"}]